coderdata/__init__.py
coderdata/_version.py
coderdata/cli.py
coderdata/dataset.yml
coderdata/dataset/__init__.py
coderdata/dataset/dataset.py
coderdata/download/__init__.py
coderdata/download/downloader.py
coderdata/utils/__init__.py
coderdata/utils/stats.py
coderdata/utils/utils.py
coderdata-2.2.1.dist-info/METADATA
coderdata-2.2.1.dist-info/WHEEL
coderdata-2.2.1.dist-info/entry_points.txt
coderdata-2.2.1.dist-info/licenses/LICENSE
coderdata-2.2.1.dist-info/RECORD
