Metadata-Version: 2.4
Name: coderdata
Version: 2.2.1
Summary: A package to download, load, and process multiple benchmark multi-omic drug response datasets
Project-URL: Homepage, https://github.com/PNNL-CompBio/candleDataProcessing
Project-URL: Documentation, https://pnnl-compbio.github.io/coderdata/
Project-URL: Repository, https://github.com/PNNL-CompBio/coderdata.git
Project-URL: Issues, https://github.com/PNNL-CompBio/coderdata/issues
Author-email: Jeremy Jacobson <jeremy.jacobson@pnnl.gov>, Yannick Mahlich <yannick.mahlich@pnnl.gov>, Sara Gosline <sara.gosline@pnnl.gov>
License: 2-clause BSD
License-File: LICENSE
Classifier: License :: OSI Approved :: BSD License
Classifier: Operating System :: OS Independent
Classifier: Programming Language :: Python :: 3 :: Only
Classifier: Programming Language :: Python :: 3.9
Classifier: Programming Language :: Python :: 3.10
Classifier: Programming Language :: Python :: 3.11
Classifier: Programming Language :: Python :: 3.12
Classifier: Programming Language :: Python :: 3.13
Classifier: Topic :: Scientific/Engineering
Classifier: Topic :: Scientific/Engineering :: Bio-Informatics
Requires-Python: >=3.9
Requires-Dist: numpy
Requires-Dist: pandas
Requires-Dist: pyyaml
Requires-Dist: requests
Requires-Dist: scikit-learn
